toploc/__init__.py
toploc/poly.py
toploc/utils.py
toploc/C/csrc/__init__.py
toploc/C/csrc/ndd.cpp
toploc/C/csrc/ndd.cpython-310-aarch64-linux-gnu.so
toploc/C/csrc/ndd.pyi
toploc/C/csrc/poly.cpp
toploc/C/csrc/poly.cpython-310-aarch64-linux-gnu.so
toploc/C/csrc/poly.pyi
toploc/C/csrc/utils.cpp
toploc/C/csrc/utils.cpython-310-aarch64-linux-gnu.so
toploc/C/csrc/utils.pyi
toploc-0.1.6.dist-info/METADATA
toploc-0.1.6.dist-info/WHEEL
toploc-0.1.6.dist-info/top_level.txt
toploc-0.1.6.dist-info/RECORD
toploc-0.1.6.dist-info/licenses/LICENSE
