Metadata-Version: 2.4
Name: toploc
Version: 0.1.6
Summary: Lib for generating model inference and training proofs
Author-email: Jack Min Ong <ongjackm@gmail.com>
License: MIT
Project-URL: Documentation, https://github.com/PrimeIntellect-ai/toploc
Project-URL: Repository, https://github.com/PrimeIntellect-ai/toploc
Project-URL: Issues, https://github.com/PrimeIntellect-ai/toploc/issues
Classifier: Programming Language :: Python :: 3
Classifier: License :: OSI Approved :: MIT License
Classifier: Operating System :: OS Independent
Requires-Python: >=3.9
License-File: LICENSE
Requires-Dist: setuptools
Requires-Dist: torch
Requires-Dist: numpy
Dynamic: license-file
